{
  "word_count": 364,
  "unique_word_count": 188,
  "sentence_count": 1,
  "avg_words_per_sentence": 364.0,
  "readability": null,
  "sentiment_analysis": null,
  "topic_keywords": [
    "and",
    "the",
    "she",
    "would",
    "her",
    "because",
    "was",
    "cup",
    "admit",
    "How"
  ],
  "repetition_analysis": {
    "repetition_ratio": 0.48351648351648346,
    "most_common_words": [
      [
        "and",
        17
      ],
      [
        "the",
        14
      ],
      [
        "she",
        11
      ],
      [
        "would",
        5
      ],
      [
        "her",
        5
      ]
    ]
  }
}