{
  "track_id": "369",
  "provenance": {
    "original_audio_path": "../../data/raw/MIREX-like_mood/dataset/Audio/369.mp3",
    "original_lyrics_path": "../../data/raw/MIREX-like_mood/dataset/Lyrics/369.txt",
    "processing_date": "2025-10-24T22:16:40.634198+00:00",
    "script_version": "1.0.0"
  },
  "audio_properties": {
    "original_sr": 44100,
    "target_sr": 44100,
    "channels": 2
  },
  "audio_features": {
    "duration_seconds": 4.5351473922902495e-05,
    "integrated_loudness_lufs": -Infinity,
    "snr_percentile_db": 5.916790008544922,
    "clipping_percentage": 0.0,
    "rms_energy_mean": 1.75702837168501e-06,
    "rms_energy_std": 0.0,
    "zcr_mean": 0.0,
    "zcr_std": 0.0,
    "spectral_centroid_mean": 8962.098787795558,
    "spectral_bandwidth_mean": 5909.904646560364,
    "mfcc_0_mean": -1062.844970703125,
    "mfcc_0_std": 0.0,
    "mfcc_1_mean": 16.466625213623047,
    "mfcc_1_std": 0.0,
    "mfcc_2_mean": -11.952059745788574,
    "mfcc_2_std": 0.0,
    "mfcc_3_mean": 7.9710693359375,
    "mfcc_3_std": 0.0,
    "mfcc_4_mean": -5.348730087280273,
    "mfcc_4_std": 0.0,
    "mfcc_5_mean": 3.5271482467651367,
    "mfcc_5_std": 0.0,
    "mfcc_6_mean": -2.3827433586120605,
    "mfcc_6_std": 0.0,
    "mfcc_7_mean": 1.517425298690796,
    "mfcc_7_std": 0.0,
    "mfcc_8_mean": -1.0116432905197144,
    "mfcc_8_std": 0.0,
    "mfcc_9_mean": 0.5442306399345398,
    "mfcc_9_std": 0.0,
    "mfcc_10_mean": -0.3306608200073242,
    "mfcc_10_std": 0.0,
    "mfcc_11_mean": 0.05733434855937958,
    "mfcc_11_std": 0.0,
    "mfcc_12_mean": 0.0159137099981308,
    "mfcc_12_std": 0.0,
    "vocal_dominance_score_hpss": 0.5
  },
  "lyrics_features": {
    "cleaned_text": "If I could save Time in a bottle The first thing that I'd like to do Is to save every day 'Til Eternity passes away Just to spend them with you If I could make days last forever If words could make wishes come true I'd save every day like a treasure and then, Again, I would spend them with you CHORUS: But there never seems to be enough time To do the things you want to do Once you find them I've looked around enough to know That you're the one I want to go Through time with If I had a box just for wishes And dreams that had never come true The box would be empty Except for the memory Of how they were answered by you (Repeat Chorus)",
    "language_code": "en",
    "completeness_heuristic": 1.0,
    "word_count": 132,
    "char_count": 639,
    "sentence_count": 1,
    "type_token_ratio": 0.6136363636363636
  },
  "is_high_quality": false,
  "normalized_audio_path": "processed_dataset/MOOD/audio_rejected/369.wav"
}