{
  "track_id": "123",
  "provenance": {
    "original_audio_path": "../../data/raw/MIREX-like_mood/dataset/Audio/123.mp3",
    "original_lyrics_path": "../../data/raw/MIREX-like_mood/dataset/Lyrics/123.txt",
    "processing_date": "2025-10-24T22:16:41.536034+00:00",
    "script_version": "1.0.0"
  },
  "audio_properties": {
    "original_sr": 44100,
    "target_sr": 44100,
    "channels": 2
  },
  "audio_features": {
    "duration_seconds": 4.5351473922902495e-05,
    "integrated_loudness_lufs": -Infinity,
    "snr_percentile_db": 8.730072021484375,
    "clipping_percentage": 0.0,
    "rms_energy_mean": 2.5669635306257987e-06,
    "rms_energy_std": 0.0,
    "zcr_mean": 0.0,
    "zcr_std": 0.0,
    "spectral_centroid_mean": 9464.73405621664,
    "spectral_bandwidth_mean": 6113.988258830556,
    "mfcc_0_mean": -1027.885986328125,
    "mfcc_0_std": 0.0,
    "mfcc_1_mean": 13.596124649047852,
    "mfcc_1_std": 0.0,
    "mfcc_2_mean": -9.774343490600586,
    "mfcc_2_std": 0.0,
    "mfcc_3_mean": 6.440834045410156,
    "mfcc_3_std": 0.0,
    "mfcc_4_mean": -4.3318376541137695,
    "mfcc_4_std": 0.0,
    "mfcc_5_mean": 2.899325132369995,
    "mfcc_5_std": 0.0,
    "mfcc_6_mean": -2.051145076751709,
    "mfcc_6_std": 0.0,
    "mfcc_7_mean": 1.4094431400299072,
    "mfcc_7_std": 0.0,
    "mfcc_8_mean": -1.072038173675537,
    "mfcc_8_std": 0.0,
    "mfcc_9_mean": 0.7296324968338013,
    "mfcc_9_std": 0.0,
    "mfcc_10_mean": -0.6067112684249878,
    "mfcc_10_std": 0.0,
    "mfcc_11_mean": 0.39691856503486633,
    "mfcc_11_std": 0.0,
    "mfcc_12_mean": -0.36539390683174133,
    "mfcc_12_std": 0.0,
    "vocal_dominance_score_hpss": 0.5
  },
  "lyrics_features": {
    "cleaned_text": "Come up screaming Come up screaming I've never seen you look like this without a reason Another promise fallen through Another season passes by you I never took the smile away from anybody's face And that's a desperate way to look For someone who is still a child In a big country dreams stay with you Like a lover's voice fires the mountainside Stay alive I thought that pain and truth were things that really mattered But you can't stay here with every single hope you had shattered I'm not expecting to grow flowers in a desert But I can live and breathe And see the sun in wintertime In a big country dreams stay with you Like a lover's voice fires the mountainside Stay alive Stay alive So take that look out of here it doesn't fit you Because it's happened doesn't mean you've been discarded Pull up your head off the floor?come up screaming Cry out for everything you ever might have wanted I thought that pain and truth were things that really mattered But you can't stay here with every single hope you had shattered I'm not expecting to grow flowers in a desert But I can live and breathe And see the sun in wintertime In a big country dreams stay with you Like a lover's voice fires the mountainside Stay alive Stay alive Stay alive",
    "language_code": "en",
    "completeness_heuristic": 1.0,
    "word_count": 230,
    "char_count": 1243,
    "sentence_count": 2,
    "type_token_ratio": 0.46956521739130436
  },
  "is_high_quality": false,
  "normalized_audio_path": "processed_dataset/MOOD/audio_rejected/123.wav"
}