{
  "track_id": "475",
  "provenance": {
    "original_audio_path": "../../data/raw/MIREX-like_mood/dataset/Audio/475.mp3",
    "original_lyrics_path": "../../data/raw/MIREX-like_mood/dataset/Lyrics/475.txt",
    "processing_date": "2025-10-24T22:16:44.099619+00:00",
    "script_version": "1.0.0"
  },
  "audio_properties": {
    "original_sr": 44100,
    "target_sr": 44100,
    "channels": 2
  },
  "audio_features": {
    "duration_seconds": 4.5351473922902495e-05,
    "integrated_loudness_lufs": -Infinity,
    "snr_percentile_db": 5.409541130065918,
    "clipping_percentage": 0.0,
    "rms_energy_mean": 0.000143138924613595,
    "rms_energy_std": 0.0,
    "zcr_mean": 0.0,
    "zcr_std": 0.0,
    "spectral_centroid_mean": 8863.448089976031,
    "spectral_bandwidth_mean": 5861.56098372513,
    "mfcc_0_mean": -631.06689453125,
    "mfcc_0_std": 0.0,
    "mfcc_1_mean": 18.34332275390625,
    "mfcc_1_std": 0.0,
    "mfcc_2_mean": -13.707420349121094,
    "mfcc_2_std": 0.0,
    "mfcc_3_mean": 9.603706359863281,
    "mfcc_3_std": 0.0,
    "mfcc_4_mean": -6.872358322143555,
    "mfcc_4_std": 0.0,
    "mfcc_5_mean": 4.955266952514648,
    "mfcc_5_std": 0.0,
    "mfcc_6_mean": -3.724954128265381,
    "mfcc_6_std": 0.0,
    "mfcc_7_mean": 2.780879497528076,
    "mfcc_7_std": 0.0,
    "mfcc_8_mean": -2.2014927864074707,
    "mfcc_8_std": 0.0,
    "mfcc_9_mean": 1.6641390323638916,
    "mfcc_9_std": 0.0,
    "mfcc_10_mean": -1.3834176063537598,
    "mfcc_10_std": 0.0,
    "mfcc_11_mean": 1.044994831085205,
    "mfcc_11_std": 0.0,
    "mfcc_12_mean": -0.9082543849945068,
    "mfcc_12_std": 0.0,
    "vocal_dominance_score_hpss": 0.5
  },
  "lyrics_features": {
    "cleaned_text": "The boy with the thorn in his side Behind the hatred there lies A murderous desire for love How can they look into my eyes And still they don't believe me ? How can they hear me say those words Still they don't believe me ? And if they don't believe me now Will they ever believe me ? And if they don't believe me now Will they ever, they ever, believe me ? Oh no ... Oh ... The boy with the thorn in his side Behind the hatred there lies A plundering desire for love How can they see the love in our eyes And still they don't believe us ? And after all this time, ah They don't want to believe us And if they don't believe us now Will they ever believe us ? And when you want to live How do you start ? Where do you go ? Who do you need to know ? Oh no no no ... Oh ... Oh no ... Oh ... La ...",
    "language_code": "en",
    "completeness_heuristic": 0.8,
    "word_count": 175,
    "char_count": 794,
    "sentence_count": 17,
    "type_token_ratio": 0.37714285714285717
  },
  "is_high_quality": false,
  "normalized_audio_path": "processed_dataset/MOOD/audio_rejected/475.wav"
}