{
  "track_id": "606",
  "provenance": {
    "original_audio_path": "../../data/raw/MIREX-like_mood/dataset/Audio/606.mp3",
    "original_lyrics_path": "../../data/raw/MIREX-like_mood/dataset/Lyrics/606.txt",
    "processing_date": "2025-10-24T22:16:44.496767+00:00",
    "script_version": "1.0.0"
  },
  "audio_properties": {
    "original_sr": 44100,
    "target_sr": 44100,
    "channels": 2
  },
  "audio_features": {
    "duration_seconds": 4.5351473922902495e-05,
    "integrated_loudness_lufs": -Infinity,
    "snr_percentile_db": 16.461496353149414,
    "clipping_percentage": 0.0,
    "rms_energy_mean": 4.1771372139010055e-07,
    "rms_energy_std": 0.0,
    "zcr_mean": 0.0,
    "zcr_std": 0.0,
    "spectral_centroid_mean": 10357.966664920126,
    "spectral_bandwidth_mean": 6325.583181908366,
    "mfcc_0_mean": -1131.370849609375,
    "mfcc_0_std": 0.0,
    "mfcc_1_mean": 0.0,
    "mfcc_1_std": 0.0,
    "mfcc_2_mean": 0.0,
    "mfcc_2_std": 0.0,
    "mfcc_3_mean": 0.0,
    "mfcc_3_std": 0.0,
    "mfcc_4_mean": 0.0,
    "mfcc_4_std": 0.0,
    "mfcc_5_mean": 0.0,
    "mfcc_5_std": 0.0,
    "mfcc_6_mean": 0.0,
    "mfcc_6_std": 0.0,
    "mfcc_7_mean": 0.0,
    "mfcc_7_std": 0.0,
    "mfcc_8_mean": 0.0,
    "mfcc_8_std": 0.0,
    "mfcc_9_mean": 0.0,
    "mfcc_9_std": 0.0,
    "mfcc_10_mean": 0.0,
    "mfcc_10_std": 0.0,
    "mfcc_11_mean": 0.0,
    "mfcc_11_std": 0.0,
    "mfcc_12_mean": 0.0,
    "mfcc_12_std": 0.0,
    "vocal_dominance_score_hpss": 0.5000000596046448
  },
  "lyrics_features": {
    "cleaned_text": "Sex and drugs and rock and roll Is all my brain and body need Sex and drugs and rock and roll Are very good indeed Keep your silly ways or throw them out the window The wisdom of your ways, I've been there and I know Lots of other ways, what a jolly bad show If all you ever do is business you don't like Sex and drugs and rock and roll Sex and drugs and rock and roll Sex and drugs and rock and roll Is very good indeed Every bit of clothing ought to make you pretty You can cut the clothing, grey is such a pity I should wear the clothing of Mr. Walter Mitty See my tailor, he's called Simon, I know it's going to fit Here's a little piece of advice You're quite welcome it is free Don't do nothing that is cut price You know what that'll make you be They will try their tricky device Trap you with the ordinary Get your teeth into a small slice The cake of liberty Sex and drugs and rock and roll Sex and drugs and rock and roll Sex and drugs and rock and roll Sex and drugs and rock and roll Sex and drugs and rock and roll Sex and drugs and rock and roll Sex and drugs and rock and roll Sex and drugs and rock and roll Sex, drugs, rock, roll Sex, drugs, rock, roll",
    "language_code": "en",
    "completeness_heuristic": 1.0,
    "word_count": 242,
    "char_count": 1169,
    "sentence_count": 2,
    "type_token_ratio": 0.45454545454545453
  },
  "is_high_quality": true,
  "normalized_audio_path": "processed_dataset/MOOD/audio_normalized/606.wav"
}