{
  "track_id": "783",
  "provenance": {
    "original_audio_path": "../../data/raw/MIREX-like_mood/dataset/Audio/783.mp3",
    "original_lyrics_path": "../../data/raw/MIREX-like_mood/dataset/Lyrics/783.txt",
    "processing_date": "2025-10-24T22:16:41.622722+00:00",
    "script_version": "1.0.0"
  },
  "audio_properties": {
    "original_sr": 44100,
    "target_sr": 44100,
    "channels": 2
  },
  "audio_features": {
    "duration_seconds": 4.5351473922902495e-05,
    "integrated_loudness_lufs": -Infinity,
    "snr_percentile_db": 0.16786789894104004,
    "clipping_percentage": 0.0,
    "rms_energy_mean": 0.0002092577051371336,
    "rms_energy_std": 0.0,
    "zcr_mean": 0.0,
    "zcr_std": 0.0,
    "spectral_centroid_mean": 8009.57261146198,
    "spectral_bandwidth_mean": 5287.924328313381,
    "mfcc_0_mean": -595.3780517578125,
    "mfcc_0_std": 0.0,
    "mfcc_1_mean": 26.37436294555664,
    "mfcc_1_std": 0.0,
    "mfcc_2_mean": -21.055883407592773,
    "mfcc_2_std": 0.0,
    "mfcc_3_mean": 16.258556365966797,
    "mfcc_3_std": 0.0,
    "mfcc_4_mean": -12.913141250610352,
    "mfcc_4_std": 0.0,
    "mfcc_5_mean": 10.466175079345703,
    "mfcc_5_std": 0.0,
    "mfcc_6_mean": -8.77304458618164,
    "mfcc_6_std": 0.0,
    "mfcc_7_mean": 7.4226484298706055,
    "mfcc_7_std": 0.0,
    "mfcc_8_mean": -6.483234405517578,
    "mfcc_8_std": 0.0,
    "mfcc_9_mean": 5.625094413757324,
    "mfcc_9_std": 0.0,
    "mfcc_10_mean": -5.0572404861450195,
    "mfcc_10_std": 0.0,
    "mfcc_11_mean": 4.460518836975098,
    "mfcc_11_std": 0.0,
    "mfcc_12_mean": -4.0906829833984375,
    "mfcc_12_std": 0.0,
    "vocal_dominance_score_hpss": 0.5000001788139343
  },
  "lyrics_features": {
    "cleaned_text": "Some folks are born, made to wave the flag Oh, they're red, white and blue And when the band plays \"Hail to the chief\" Oh, they point the cannon at you, Lord It ain't me, it ain't me, I ain't no senator's son, son It ain't me, it ain't me, I ain't no fortunate one, no Some folks are born, silver spoon in hand Lord, don't they help themselves, yo But when the taxman comes to the door Lord, the house looks like a rummage sale, yeah It ain't me, it ain't me, I ain't no millionaire's son, no, no It ain't me, it ain't me, I ain't no fortunate one, no Yeah, yeah Some folks inherit star spangled eyes Ooh, they send you down to war, Lord And when you ask them, \"How much should we give?\" Ooh, they only answer \"More! more! more!\", yo It ain't me, it ain't me, I ain't no military son, son It ain't me, it ain't me, I ain't no fortunate one, one It ain't me, it ain't me, I ain't no fortunate one, no, no, no It ain't me, it ain't me, I ain't no fortunate son, no, no, no",
    "language_code": "en",
    "completeness_heuristic": 1.0,
    "word_count": 198,
    "char_count": 970,
    "sentence_count": 5,
    "type_token_ratio": 0.42424242424242425
  },
  "is_high_quality": false,
  "normalized_audio_path": "processed_dataset/MOOD/audio_rejected/783.wav"
}