{
  "track_id": "870",
  "provenance": {
    "original_audio_path": "../../data/raw/MIREX-like_mood/dataset/Audio/870.mp3",
    "original_lyrics_path": "../../data/raw/MIREX-like_mood/dataset/Lyrics/870.txt",
    "processing_date": "2025-10-24T22:16:39.485878+00:00",
    "script_version": "1.0.0"
  },
  "audio_properties": {
    "original_sr": 44100,
    "target_sr": 44100,
    "channels": 2
  },
  "audio_features": {
    "duration_seconds": 4.5351473922902495e-05,
    "integrated_loudness_lufs": -Infinity,
    "snr_percentile_db": 1.6934572458267212,
    "clipping_percentage": 0.0,
    "rms_energy_mean": 8.235307973336603e-07,
    "rms_energy_std": 0.0,
    "zcr_mean": 0.00048828125,
    "zcr_std": 0.0,
    "spectral_centroid_mean": 13882.353122551529,
    "spectral_bandwidth_mean": 5422.7784201017,
    "mfcc_0_mean": -1130.7161865234375,
    "mfcc_0_std": 0.0,
    "mfcc_1_mean": -0.9191287755966187,
    "mfcc_1_std": 0.0,
    "mfcc_2_mean": 0.8995815515518188,
    "mfcc_2_std": 0.0,
    "mfcc_3_mean": -0.8676722645759583,
    "mfcc_3_std": 0.0,
    "mfcc_4_mean": 0.8244057893753052,
    "mfcc_4_std": 0.0,
    "mfcc_5_mean": -0.7710907459259033,
    "mfcc_5_std": 0.0,
    "mfcc_6_mean": 0.7093578577041626,
    "mfcc_6_std": 0.0,
    "mfcc_7_mean": -0.641028881072998,
    "mfcc_7_std": 0.0,
    "mfcc_8_mean": 0.5680882334709167,
    "mfcc_8_std": 0.0,
    "mfcc_9_mean": -0.4925941824913025,
    "mfcc_9_std": 0.0,
    "mfcc_10_mean": 0.41658270359039307,
    "mfcc_10_std": 0.0,
    "mfcc_11_mean": -0.34201693534851074,
    "mfcc_11_std": 0.0,
    "mfcc_12_mean": 0.27070891857147217,
    "mfcc_12_std": 0.0,
    "vocal_dominance_score_hpss": 0.4999999701976776
  },
  "lyrics_features": {
    "cleaned_text": "Crack of dawn Cindy's movin' on Talking Cindy to everyone Until she's had her fun She has me We twist the sun and sea Still she's talking to everyone Cindy's had her fun Though I've heard it before Still I need you more and more But I just can't get away Cindy kills me every day And I tried and I tried But you looked right through me Knife to my head when she talks so sweetly Knife in my head when I think of Cindy Knife in my head is the taste of Cindy",
    "language_code": "en",
    "completeness_heuristic": 1.0,
    "word_count": 95,
    "char_count": 456,
    "sentence_count": 1,
    "type_token_ratio": 0.631578947368421
  },
  "is_high_quality": false,
  "normalized_audio_path": "processed_dataset/MOOD/audio_rejected/870.wav"
}