{
  "word_count": 200,
  "unique_word_count": 156,
  "sentence_count": 1,
  "avg_words_per_sentence": 200.0,
  "readability": null,
  "sentiment_analysis": null,
  "topic_keywords": [
    "comme",
    "les",
    "des",
    "pas",
    "QSM",
    "sur",
    "est",
    "baron",
    "plus",
    "ils"
  ],
  "repetition_analysis": {
    "repetition_ratio": 0.21999999999999997,
    "most_common_words": [
      [
        "comme",
        5
      ],
      [
        "les",
        4
      ],
      [
        "des",
        4
      ],
      [
        "pas",
        4
      ],
      [
        "QSM",
        3
      ]
    ]
  }
}