{
  "track_id": "Da_wurdest_du_geboren_-_Alice_Tlustos_",
  "provenance": {
    "original_audio_path": "../../jamando_processed/transcoded/Da_wurdest_du_geboren_-_Alice_Tlustos_.wav",
    "original_lyrics_path": "../../data/raw/jam-alt/lyrics/Da_wurdest_du_geboren_-_Alice_Tlustos_.txt",
    "processing_date": "2025-10-24T22:01:18.092210+00:00",
    "script_version": "1.0.0"
  },
  "audio_properties": {
    "original_sr": 22050,
    "target_sr": 44100,
    "channels": 1
  },
  "audio_features": {
    "duration_seconds": 207.36108843537414,
    "integrated_loudness_lufs": -15.670819206060209,
    "snr_percentile_db": 11.517605400035546,
    "clipping_percentage": 0.0,
    "rms_energy_mean": 0.0611145943403244,
    "rms_energy_std": 0.03429657593369484,
    "zcr_mean": 0.05200448187566486,
    "zcr_std": 0.05060538007672484,
    "spectral_centroid_mean": 2108.616882542068,
    "spectral_bandwidth_mean": 2351.5603560451277,
    "mfcc_0_mean": -276.1726750810329,
    "mfcc_0_std": 88.93188928882489,
    "mfcc_1_mean": 155.48019233182174,
    "mfcc_1_std": 34.23699354894476,
    "mfcc_2_mean": -35.9545737712935,
    "mfcc_2_std": 29.956222934250672,
    "mfcc_3_mean": 51.83703970088336,
    "mfcc_3_std": 23.668134194639457,
    "mfcc_4_mean": -0.6118481524589625,
    "mfcc_4_std": 17.90416648342698,
    "mfcc_5_mean": 11.91182448711453,
    "mfcc_5_std": 14.057842131306513,
    "mfcc_6_mean": 4.10905439862972,
    "mfcc_6_std": 12.455420607093687,
    "mfcc_7_mean": -6.817833230960116,
    "mfcc_7_std": 10.139774446019098,
    "mfcc_8_mean": 15.358781295533712,
    "mfcc_8_std": 13.785511608111507,
    "mfcc_9_mean": -9.462947002894007,
    "mfcc_9_std": 10.072536378027895,
    "mfcc_10_mean": 8.127897369159387,
    "mfcc_10_std": 11.310078265742488,
    "mfcc_11_mean": -3.0887716449493974,
    "mfcc_11_std": 9.299763974954347,
    "mfcc_12_mean": -5.035299866052332,
    "mfcc_12_std": 8.710202146284924,
    "vocal_dominance_score_hpss": 0.8770281424831863
  },
  "lyrics_features": {
    "cleaned_text": "Hoffnungslos im Dunkel meines Seins raste ich dahin Suchte nach dem Sinn meines Lebens Voller Angst war ich gefangen, suchte nach dem Ziel Hasste dieses Spiel meines Lebens Wahrheit war mir fremd, zu schwer, Anerkennung galt Denn mein Herz war kalt, ohne Liebe Jesus, da wurdest du geboren Licht f\u00fcr meine Dunkelheit Hoffnung meiner kalten Seele Trost in Not und Leid, Jesus Du hast alles selbst erlebt, hast den Thron verlassen F\u00fchltest Lieben, Hassen dieser Welt Du verstehst das tiefste Leid, Blindheit weicht vor dir Schenkst dein Licht auch mir, Jesus F\u00fcr dein Kommen ehr' ich dich, Majest\u00e4t vom All Legst dich in den Stall meines Lebens Jesus, du wirst in mir geboren Licht f\u00fcr meine Dunkelheit Hoffnung meiner kalten Seele Trost in Not und Leid, Jesus Jesus, du wirst in mir geboren Licht f\u00fcr meine Dunkelheit Hoffnung meiner kalten Seele Trost in Not und Leid, Jesus, Jesus",
    "language_code": "de",
    "completeness_heuristic": 1.0,
    "word_count": 148,
    "char_count": 881,
    "sentence_count": 1,
    "type_token_ratio": 0.6013513513513513
  },
  "is_high_quality": false,
  "normalized_audio_path": "processed_dataset/jam-alt/audio_rejected/Da_wurdest_du_geboren_-_Alice_Tlustos_.wav"
}