{
  "track_id": "kr018a",
  "provenance": {
    "original_audio_path": "../../data/raw/CSD/korean/wav/kr018a.wav",
    "original_lyrics_path": "../../data/raw/CSD/korean/lyric/kr018a.txt",
    "processing_date": "2025-10-24T22:19:49.503841+00:00",
    "script_version": "1.0.0"
  },
  "audio_properties": {
    "original_sr": 44100,
    "target_sr": 44100,
    "channels": 2
  },
  "audio_features": {
    "duration_seconds": 4.5351473922902495e-05,
    "integrated_loudness_lufs": -Infinity,
    "snr_percentile_db": 0.013344920240342617,
    "clipping_percentage": 0.0,
    "rms_energy_mean": 8.832245725898247e-07,
    "rms_energy_std": 0.0,
    "zcr_mean": 0.0,
    "zcr_std": 0.0,
    "spectral_centroid_mean": 8006.428537572819,
    "spectral_bandwidth_mean": 5284.803746846929,
    "mfcc_0_mean": -1118.7379150390625,
    "mfcc_0_std": 0.0,
    "mfcc_1_mean": 7.11383056640625,
    "mfcc_1_std": 0.0,
    "mfcc_2_mean": -3.116344451904297,
    "mfcc_2_std": 0.0,
    "mfcc_3_mean": 0.28365546464920044,
    "mfcc_3_std": 0.0,
    "mfcc_4_mean": 0.749886155128479,
    "mfcc_4_std": 0.0,
    "mfcc_5_mean": -0.8513731360435486,
    "mfcc_5_std": 0.0,
    "mfcc_6_mean": 0.4301304817199707,
    "mfcc_6_std": 0.0,
    "mfcc_7_mean": -0.06598007678985596,
    "mfcc_7_std": 0.0,
    "mfcc_8_mean": -0.2541126608848572,
    "mfcc_8_std": 0.0,
    "mfcc_9_mean": 0.2455061972141266,
    "mfcc_9_std": 0.0,
    "mfcc_10_mean": -0.2268362045288086,
    "mfcc_10_std": 0.0,
    "mfcc_11_mean": 0.00809486210346222,
    "mfcc_11_std": 0.0,
    "mfcc_12_mean": 0.04591858386993408,
    "mfcc_12_std": 0.0,
    "vocal_dominance_score_hpss": 0.5000003576278687
  },
  "lyrics_features": {
    "cleaned_text": "\uc6b8\uba74 \uc548 \ub3fc \uc6b8\uba74 \uc548 \ub3fc \uc0b0\ud0c0 \ud560\uc544\ubc84\uc9c0\ub294 \uc6b0\ub294 \uc560\ub4e4\uc5d4 \uc120\ubb3c\uc744 \uc548 \uc8fc\uc2e0\ub300\uc694 \uc0b0\ud0c0 \ud560\uc544\ubc84\uc9c0\ub294 \uc54c\uace0 \uacc4\uc2e0\ub300 \ub204\uac00 \ucc29\ud55c \uc564\uc9c0 \ub098\uc05c \uc564\uc9c0 \uc624\ub298 \ubc24\uc5d0 \ub2e4\ub140\uac00\uc2e0\ub300 \uc7a0 \uc798 \ub54c\ub098 \uc77c\uc5b4\ub0a0 \ub54c \uc9dc\uc99d\ub0bc \ub54c \uc7a5\ub09c\ud560 \ub54c\ub3c4 \uc0b0\ud0c0 \ud560\uc544\ubc84\uc9c0\ub294 \ubaa8\ub4e0 \uac83\uc744 \uc54c\uace0 \uacc4\uc2e0\ub300 \uc6b8\uba74 \uc548 \ub3fc \uc6b8\uba74 \uc548 \ub3fc \uc0b0\ud0c0 \ud560\uc544\ubc84\uc9c0\ub294 \uc6b0\ub9ac \ub9c8\uc744\uc744 \uc624\ub298 \ubc24\uc5d0 \ub2e4\ub140\uac00\uc2e0\ub300 \uc6b8\uba74 \uc548 \ub3fc \uc6b8\uba74 \uc548 \ub3fc \uc0b0\ud0c0 \ud560\uc544\ubc84\uc9c0\ub294 \uc6b0\ub294 \uc560\ub4e4\uc5d4 \uc120\ubb3c\uc744 \uc548 \uc8fc\uc2e0\ub300\uc694 \uc0b0\ud0c0 \ud560\uc544\ubc84\uc9c0\ub294 \uc54c\uace0 \uacc4\uc2e0\ub300 \ub204\uac00 \ucc29\ud55c \uc564\uc9c0 \ub098\uc05c \uc564\uc9c0 \uc624\ub298 \ubc24\uc5d0 \ub2e4\ub140\uac00\uc2e0\ub300 \uc7a0 \uc798 \ub54c\ub098 \uc77c\uc5b4\ub0a0 \ub54c \uc9dc\uc99d\ub0bc \ub54c \uc7a5\ub09c\ud560 \ub54c\ub3c4 \uc0b0\ud0c0 \ud560\uc544\ubc84\uc9c0\ub294 \ubaa8\ub4e0 \uac83\uc744 \uc54c\uace0 \uacc4\uc2e0\ub300 \uc6b8\uba74 \uc548 \ub3fc \uc6b8\uba74 \uc548 \ub3fc \uc0b0\ud0c0 \ud560\uc544\ubc84\uc9c0\ub294 \uc6b0\ub9ac \ub9c8\uc744\uc744 \uc624\ub298 \ubc24\uc5d0 \ub2e4\ub140\uac00\uc2e0\ub300",
    "language_code": "ko",
    "completeness_heuristic": 1.0,
    "word_count": 106,
    "char_count": 347,
    "sentence_count": 1,
    "type_token_ratio": 0.2830188679245283
  },
  "is_high_quality": false,
  "normalized_audio_path": "processed_dataset/CSD/korean/audio_rejected/kr018a.wav"
}