{
  "track_id": "kr014b",
  "provenance": {
    "original_audio_path": "../../data/raw/CSD/korean/wav/kr014b.wav",
    "original_lyrics_path": "../../data/raw/CSD/korean/lyric/kr014b.txt",
    "processing_date": "2025-10-24T22:19:49.220425+00:00",
    "script_version": "1.0.0"
  },
  "audio_properties": {
    "original_sr": 44100,
    "target_sr": 44100,
    "channels": 2
  },
  "audio_features": {
    "duration_seconds": 4.5351473922902495e-05,
    "integrated_loudness_lufs": -Infinity,
    "snr_percentile_db": 0.25624513626098633,
    "clipping_percentage": 0.0,
    "rms_energy_mean": 2.739497739767671e-09,
    "rms_energy_std": 0.0,
    "zcr_mean": 0.0,
    "zcr_std": 0.0,
    "spectral_centroid_mean": 8013.079703643457,
    "spectral_bandwidth_mean": 5291.305281975017,
    "mfcc_0_mean": -1131.370849609375,
    "mfcc_0_std": 0.0,
    "mfcc_1_mean": 0.0,
    "mfcc_1_std": 0.0,
    "mfcc_2_mean": 0.0,
    "mfcc_2_std": 0.0,
    "mfcc_3_mean": 0.0,
    "mfcc_3_std": 0.0,
    "mfcc_4_mean": 0.0,
    "mfcc_4_std": 0.0,
    "mfcc_5_mean": 0.0,
    "mfcc_5_std": 0.0,
    "mfcc_6_mean": 0.0,
    "mfcc_6_std": 0.0,
    "mfcc_7_mean": 0.0,
    "mfcc_7_std": 0.0,
    "mfcc_8_mean": 0.0,
    "mfcc_8_std": 0.0,
    "mfcc_9_mean": 0.0,
    "mfcc_9_std": 0.0,
    "mfcc_10_mean": 0.0,
    "mfcc_10_std": 0.0,
    "mfcc_11_mean": 0.0,
    "mfcc_11_std": 0.0,
    "mfcc_12_mean": 0.0,
    "mfcc_12_std": 0.0,
    "vocal_dominance_score_hpss": 0.5000001192092896
  },
  "lyrics_features": {
    "cleaned_text": "\uc6b0\ub9ac \uc544\uae30 \ubd88\uace0 \ub178\ub294 \ud558\ubaa8\ub2c8\uce74\ub294 \uc625\uc218\uc218\ub97c \uac00\uc9c0\uace0\uc11c \ub9cc\ub4e4\uc5c8\uc5b4\uc694 \uc625\uc218\uc218\uc54c \uae38\uac8c \ub450 \uc904 \ub0a8\uaca8\uac00\uc9c0\uace0 \uc6b0\ub9ac \uc544\uae30 \ud558\ubaa8\ub2c8\uce74 \ubd88\uace0 \uc788\uc5b4\uc694 \ub3c4\ub808\ubbf8\ud30c \uc194\ub77c\uc2dc\ub3c4 \uc18c\ub9ac\uac00 \uc548\ub098 \ub3c4\ubbf8\uc194\ub3c4 \ub3c4\uc194\ubbf8\ub3c4 \ub9d0\ub85c \ud558\uc9c0\uc694 \uc6b0\ub9ac \uc544\uae30 \ubd88\uace0 \ub178\ub294 \ud558\ubaa8\ub2c8\uce74\ub294 \uc625\uc218\uc218\ub97c \uac00\uc9c0\uace0\uc11c \ub9cc\ub4e4\uc5c8\uc5b4\uc694 \uc625\uc218\uc218\uc54c \uae38\uac8c \ub450 \uc904 \ub0a8\uaca8\uac00\uc9c0\uace0 \uc6b0\ub9ac \uc544\uae30 \ud558\ubaa8\ub2c8\uce74 \ubd88\uace0 \uc788\uc5b4\uc694 \ub3c4\ub808\ubbf8\ud30c \uc194\ub77c\uc2dc\ub3c4 \uc18c\ub9ac\uac00 \uc548\ub098 \ub3c4\ubbf8\uc194\ub3c4 \ub3c4\uc194\ubbf8\ub3c4 \ub9d0\ub85c \ud558\uc9c0\uc694",
    "language_code": "ko",
    "completeness_heuristic": 1.0,
    "word_count": 52,
    "char_count": 207,
    "sentence_count": 1,
    "type_token_ratio": 0.4423076923076923
  },
  "is_high_quality": false,
  "normalized_audio_path": "processed_dataset/CSD/korean/audio_rejected/kr014b.wav"
}