{
  "word_count": 403,
  "unique_word_count": 227,
  "sentence_count": 26,
  "avg_words_per_sentence": 15.5,
  "readability": null,
  "sentiment_analysis": null,
  "topic_keywords": [
    "the",
    "and",
    "you",
    "got",
    "like",
    "all",
    "just",
    "truckin'",
    "out",
    "get"
  ],
  "repetition_analysis": {
    "repetition_ratio": 0.43672456575682383,
    "most_common_words": [
      [
        "the",
        16
      ],
      [
        "and",
        15
      ],
      [
        "you",
        9
      ],
      [
        "got",
        6
      ],
      [
        "like",
        5
      ]
    ]
  }
}